{"stats":{"minecraft:dropped":{"minecraft:diamond_sword":1,"minecraft:red_concrete":1,"minecraft:leather_chestplate":1,"minecraft:black_dye":3,"minecraft:smooth_stone_slab":1,"minecraft:leather_boots":1,"minecraft:leather_leggings":1,"minecraft:leather_helmet":1},"minecraft:custom":{"minecraft:time_since_rest":44001,"minecraft:sprint_one_cm":19950,"minecraft:walk_one_cm":227036,"minecraft:drop":8,"minecraft:damage_dealt":70,"minecraft:interact_with_beacon":2,"minecraft:interact_with_crafting_table":2,"minecraft:fly_one_cm":483059,"minecraft:open_chest":1,"minecraft:crouch_one_cm":361,"minecraft:play_one_minute":64486,"minecraft:deaths":1,"minecraft:sneak_time":91,"minecraft:aviate_one_cm":61864,"minecraft:jump":384,"minecraft:leave_game":31,"minecraft:walk_on_water_one_cm":536,"minecraft:time_since_death":43958,"minecraft:climb_one_cm":297},"minecraft:crafted":{"minecraft:leather_leggings":1,"minecraft:leather_boots":1,"minecraft:leather_chestplate":1,"minecraft:leather_helmet":1},"minecraft:picked_up":{"minecraft:smooth_stone_slab":1,"minecraft:polished_diorite":1,"minecraft:quartz_stairs":1},"minecraft:used":{"minecraft:emerald_ore":1,"minecraft:glass":93,"minecraft:piston":4,"minecraft:lever":3,"minecraft:lava_bucket":29,"minecraft:iron_ore":3,"minecraft:firework_rocket":1,"minecraft:red_sand":4,"minecraft:bricks":1,"minecraft:coal_ore":1,"minecraft:orange_concrete":1,"minecraft:red_concrete":1,"minecraft:oak_sign":1,"minecraft:spruce_trapdoor":6,"minecraft:zombie_spawn_egg":12,"minecraft:smooth_quartz":22,"minecraft:beacon":10,"minecraft:quartz_stairs":12,"minecraft:gold_ore":6,"minecraft:bedrock":22,"minecraft:glowstone":4,"minecraft:diamond_sword":1,"minecraft:lime_concrete":1,"minecraft:potion":5,"minecraft:oak_slab":13,"minecraft:crafting_table":1,"minecraft:glass_pane":33,"minecraft:smooth_stone_slab":262,"minecraft:acacia_button":3,"minecraft:painting":7}},"DataVersion":1976}